{
  "vertices": [
    {
      "_collection": "flow",
      "_id": "5234a93f-24c6-42b7-8923-0268e19e5b46",
      "_origin": true,
      "_x": 0,
      "_y": 0,
      "languages": [
        "en",
        "de"
      ],
      "topic": {
        "en": "Welcome",
        "de": "Willkommen"
      },
      "author": "Wanderer.ai",
      "license": "MIT",
      "builder": "wanderer.ai",
      "target": "web",
      "version": "0.0.1",
      "time": "2021-01-14T15:21:52.596Z"
    },
    {
      "message": {
        "en": "Hi! 👋 My name is Wanderer.",
        "de": "Hi! 👋 Mein Name ist Wanderer."
      },
      "_id": "ea900e19-cf32-4ee0-bf05-b54314367aca",
      "_collection": "message",
      "_origin": false,
      "_x": 216.81403525683768,
      "_y": 221.12041641603247
    },
    {
      "message": {
        "en": "You are currently in the tutorial",
        "de": "Du befindest dich gerade im Tutorial"
      },
      "_id": "c2aa7d39-0503-4450-b945-b06ab813601e",
      "_collection": "message",
      "_origin": false,
      "_x": 127.53919672669068,
      "_y": 565.7394370096831
    },
    {
      "message": {
        "en": "I just activated the navigation for you. There you can change the language, restart the chat or switch to the tutorial overview.",
        "de": "Ich habe gerade die Navigation für dich aktiviert. Dort kannst du die Sprache ändern, den Chat neu starten oder zur Tutorial-Übersicht wechseln."
      },
      "_id": "c836a299-a712-4845-9027-22c0df41d19a",
      "_collection": "message",
      "_origin": false,
      "_x": 155.0724298295429,
      "_y": 1333.7024007788907
    },
    {
      "url": "https://raw.githubusercontent.com/wanderer-ai/wanderer-flows/master/tutorial/partials/navigation.json",
      "label": {
        "de": "Navigation",
        "en": "Navigation"
      },
      "_id": "1c5b939c-e9f0-4c81-91db-ffd27afd712c",
      "_collection": "import",
      "_origin": false,
      "_x": -2971.733341221154,
      "_y": -1456.1097883414786
    },
    {
      "question": {
        "en": "Please choose your language!",
        "de": "Bitte wähle deine Sprache!"
      },
      "_id": "c0c3ba23-db3b-4526-9e4d-1fc10671541e",
      "_collection": "question",
      "_origin": false,
      "_x": -400.05383124417665,
      "_y": 855.343941360608,
      "drawAttention": true
    },
    {
      "suggestion": {
        "de": "🇩🇪 Deutsch",
        "en": "🇩🇪 Deutsch"
      },
      "type": "button",
      "name": "",
      "priority": "40",
      "_id": "3eb9aa79-8138-4e67-a31e-962e0747d40c",
      "_collection": "suggestion",
      "_origin": false,
      "_x": -695.153649924395,
      "_y": 959.6877794257871
    },
    {
      "suggestion": {
        "de": "🇬🇧 English",
        "en": "🇬🇧 English"
      },
      "type": "button",
      "name": "",
      "priority": 50,
      "_id": "8c933433-27ec-4445-b6be-932b5be78c40",
      "_collection": "suggestion",
      "_origin": false,
      "_x": -548.4155093258527,
      "_y": 1087.8202473456631
    },
    {
      "switchToLanguage": "de",
      "_id": "c38feca5-1bfb-47f3-87bd-b83a8624503f",
      "_collection": "language",
      "_origin": false,
      "_x": -1041.2205411067303,
      "_y": 1092.328637945028
    },
    {
      "switchToLanguage": "en",
      "_id": "25da1a45-d017-4f33-9f6c-1760fb9f352c",
      "_collection": "language",
      "_origin": false,
      "_x": -797.4155093258532,
      "_y": 1400.6856199490785
    },
    {
      "message": {
        "en": "Perfect!",
        "de": "Perfekt!"
      },
      "_id": "3e855d5e-ecf9-4def-94a0-2c3bad759653",
      "_collection": "message",
      "_origin": false,
      "_x": -21.062317632821685,
      "_y": 1158.4398551139723
    },
    {
      "question": {
        "en": "Ready for the first session?",
        "de": "Bereit für die erste Einheit?"
      },
      "_id": "613c27ba-6472-4702-ab1d-c9118ab8b89d",
      "_collection": "question",
      "_origin": false,
      "_x": 331.61996140755144,
      "_y": 2316.436309735888,
      "drawAttention": true
    },
    {
      "suggestion": {
        "de": "Los gehts!",
        "en": "Here we go!"
      },
      "type": "button",
      "name": "",
      "priority": 50,
      "_id": "652293fb-f2ce-42bb-b870-52a5d0a4f92d",
      "_collection": "suggestion",
      "_origin": false,
      "_x": 199.73978273562767,
      "_y": 2508.367455788318
    },
    {
      "url": "https://raw.githubusercontent.com/wanderer-ai/wanderer-flows/master/tutorial/intro/the_flow.json",
      "label": "",
      "_id": "fcc3965f-ea16-4fd9-adcb-ec68578384a7",
      "_collection": "jump",
      "_origin": false,
      "_x": -6.067634428872564,
      "_y": 2624.261515980612
    },
    {
      "message": {
        "en": "This is a live tutorial. Should you break something, you can reload the current section with the green button at the top right.",
        "de": "Das ist ein Live-Tutorial. Solltest du mal etwas kaputt machen, kannst du den aktuellen Abschnitt mit dem grünen Button ganz oben rechts neu laden."
      },
      "forgetful": false,
      "_id": "2fe13df3-1657-47a8-b352-f22ba7ceab1a",
      "_collection": "message",
      "_origin": false,
      "_x": 384.38123938656054,
      "_y": 2027.2201357784404
    },
    {
      "question": {
        "en": "Are you ready for more information?",
        "de": "Bereit für mehr Informationen?"
      },
      "hideMessages": false,
      "showInNavigation": false,
      "forgetful": false,
      "repeatable": true,
      "showAlways": false,
      "_id": "c3d8a898-3097-40b9-89e0-a1e896535542",
      "_collection": "question",
      "_origin": false,
      "_x": 318.3919972741013,
      "_y": 1624.9763747113416
    },
    {
      "suggestion": {
        "de": "Weiter",
        "en": "Continue"
      },
      "type": "button",
      "name": "",
      "priority": 50,
      "required": true,
      "_id": "f51bdce7-31b6-462b-9bb4-70a9bb764bb5",
      "_collection": "suggestion",
      "_origin": false,
      "_x": 373.3924258442304,
      "_y": 1797.739878179541
    }
  ],
  "edges": [
    {
      "type": "or",
      "priority": 10,
      "name": "",
      "expose": "",
      "method": false,
      "condition": false,
      "compareVariable": false,
      "compareCondition": "==",
      "compareValue": "",
      "_id": "974c9a75-ebaf-4fc3-b0b1-55b630f0e26e",
      "_from": "5234a93f-24c6-42b7-8923-0268e19e5b46",
      "_to": "ea900e19-cf32-4ee0-bf05-b54314367aca",
      "_collection": "leadsTo"
    },
    {
      "type": "or",
      "priority": 10,
      "name": "",
      "expose": "",
      "method": false,
      "condition": "sent",
      "compareVariable": false,
      "compareCondition": "==",
      "compareValue": "",
      "_id": "fccb0e30-ec27-4022-8a0a-4acd8f17ad40",
      "_from": "ea900e19-cf32-4ee0-bf05-b54314367aca",
      "_to": "c2aa7d39-0503-4450-b945-b06ab813601e",
      "_collection": "leadsTo"
    },
    {
      "type": "or",
      "priority": 10,
      "name": "",
      "expose": "value",
      "method": false,
      "condition": "answered",
      "compareVariable": false,
      "compareCondition": "==",
      "compareValue": "",
      "_id": "a4f8bc03-07cc-40c9-8224-90eb69c27698",
      "_from": "3eb9aa79-8138-4e67-a31e-962e0747d40c",
      "_to": "c38feca5-1bfb-47f3-87bd-b83a8624503f",
      "_collection": "leadsTo"
    },
    {
      "type": "or",
      "priority": 10,
      "name": "",
      "expose": "value",
      "method": false,
      "condition": "answered",
      "compareVariable": false,
      "compareCondition": "==",
      "compareValue": "",
      "_id": "bcad7367-e751-4254-8a85-2bfbac89cad2",
      "_from": "8c933433-27ec-4445-b6be-932b5be78c40",
      "_to": "25da1a45-d017-4f33-9f6c-1760fb9f352c",
      "_collection": "leadsTo"
    },
    {
      "type": "or",
      "priority": 10,
      "name": "",
      "expose": "answered",
      "method": false,
      "condition": "answered",
      "compareVariable": false,
      "compareCondition": "==",
      "compareValue": "",
      "_id": "eb897834-44f8-472a-b38d-540704aed7b5",
      "_from": "c0c3ba23-db3b-4526-9e4d-1fc10671541e",
      "_to": "3e855d5e-ecf9-4def-94a0-2c3bad759653",
      "_collection": "leadsTo"
    },
    {
      "type": "or",
      "priority": 10,
      "name": "",
      "expose": "",
      "method": false,
      "condition": "sent",
      "compareVariable": false,
      "compareCondition": "==",
      "compareValue": "",
      "_id": "106f0d5f-e406-46a2-867e-dc8bffe7086e",
      "_from": "3e855d5e-ecf9-4def-94a0-2c3bad759653",
      "_to": "c836a299-a712-4845-9027-22c0df41d19a",
      "_collection": "leadsTo"
    },
    {
      "type": "or",
      "priority": 10,
      "name": "",
      "expose": "answered",
      "method": false,
      "condition": "answered",
      "compareVariable": false,
      "compareCondition": "==",
      "compareValue": "",
      "_id": "dd1238a8-7fc0-4800-8dbd-db34255a6340",
      "_from": "c0c3ba23-db3b-4526-9e4d-1fc10671541e",
      "_to": "1c5b939c-e9f0-4c81-91db-ffd27afd712c",
      "_collection": "leadsTo"
    },
    {
      "type": "or",
      "priority": 10,
      "name": "",
      "expose": "value",
      "method": false,
      "condition": "answered",
      "compareVariable": false,
      "compareCondition": "==",
      "compareValue": "",
      "_id": "ad01f5b1-519c-4600-a32e-cc4d891754ba",
      "_from": "652293fb-f2ce-42bb-b870-52a5d0a4f92d",
      "_to": "fcc3965f-ea16-4fd9-adcb-ec68578384a7",
      "_collection": "leadsTo"
    },
    {
      "_id": "73809ed4-6c8f-4f7e-bc31-52e8cf8c27a0",
      "_from": "c0c3ba23-db3b-4526-9e4d-1fc10671541e",
      "_to": "8c933433-27ec-4445-b6be-932b5be78c40",
      "_collection": "isAnswerableBy"
    },
    {
      "_id": "2e7b433b-7d38-46fb-8de9-52d456be8ff7",
      "_from": "c0c3ba23-db3b-4526-9e4d-1fc10671541e",
      "_to": "3eb9aa79-8138-4e67-a31e-962e0747d40c",
      "_collection": "isAnswerableBy"
    },
    {
      "_id": "f74dcecf-10d9-45ee-b6fd-9588065bd439",
      "_from": "613c27ba-6472-4702-ab1d-c9118ab8b89d",
      "_to": "652293fb-f2ce-42bb-b870-52a5d0a4f92d",
      "_collection": "isAnswerableBy"
    },
    {
      "type": "or",
      "priority": 10,
      "name": "",
      "expose": "none",
      "condition": "sent",
      "_id": "1b32f30f-51b3-4608-b4f8-dcda77de2096",
      "_from": "c2aa7d39-0503-4450-b945-b06ab813601e",
      "_to": "c0c3ba23-db3b-4526-9e4d-1fc10671541e",
      "_collection": "leadsTo"
    },
    {
      "type": "or",
      "priority": 10,
      "name": "",
      "expose": "none",
      "condition": "sent",
      "_id": "b32c1635-65e4-44de-ac1d-b6d94179a5bf",
      "_from": "2fe13df3-1657-47a8-b352-f22ba7ceab1a",
      "_to": "613c27ba-6472-4702-ab1d-c9118ab8b89d",
      "_collection": "leadsTo"
    },
    {
      "type": "or",
      "priority": 10,
      "name": "",
      "expose": "none",
      "condition": "sent",
      "_id": "af4d8f67-7c4a-4ffc-a9b4-5b52797c19bd",
      "_from": "c836a299-a712-4845-9027-22c0df41d19a",
      "_to": "c3d8a898-3097-40b9-89e0-a1e896535542",
      "_collection": "leadsTo"
    },
    {
      "_id": "6ee5a617-29b8-48fd-8226-918c8747750e",
      "_from": "c3d8a898-3097-40b9-89e0-a1e896535542",
      "_to": "f51bdce7-31b6-462b-9bb4-70a9bb764bb5",
      "_collection": "isAnswerableBy"
    },
    {
      "type": "or",
      "priority": 10,
      "name": "",
      "expose": "none",
      "condition": "answered",
      "_id": "32a4603c-c438-42ec-8f76-7d6042447a7a",
      "_from": "f51bdce7-31b6-462b-9bb4-70a9bb764bb5",
      "_to": "2fe13df3-1657-47a8-b352-f22ba7ceab1a",
      "_collection": "leadsTo"
    }
  ]
}